{
  "experiments": [
    {
      "experiment_id": "h002-alien-s1",
      "hypothesis_id": "h002",
      "command": "python cleanrl/pqn_atari_envpool.py --env-id Alien-v5 --seed 1 --total-timesteps 40000000 --hypothesis-id h002 --experiment-id h002-alien-s1 --output-dir /runs",
      "cluster": "narval",
      "gpus": 1,
      "cpus": 8,
      "memory": "32G",
      "walltime": "11:00:00"
    },
    {
      "experiment_id": "h002-alien-s3",
      "hypothesis_id": "h002",
      "command": "python cleanrl/pqn_atari_envpool.py --env-id Alien-v5 --seed 3 --total-timesteps 40000000 --hypothesis-id h002 --experiment-id h002-alien-s3 --output-dir /runs",
      "cluster": "rorqual",
      "gpus": 1,
      "cpus": 8,
      "memory": "32G",
      "walltime": "11:00:00"
    },
    {
      "experiment_id": "h002-amidar-s1",
      "hypothesis_id": "h002",
      "command": "python cleanrl/pqn_atari_envpool.py --env-id Amidar-v5 --seed 1 --total-timesteps 40000000 --hypothesis-id h002 --experiment-id h002-amidar-s1 --output-dir /runs",
      "cluster": "nibi",
      "gpus": 1,
      "cpus": 8,
      "memory": "32G",
      "walltime": "11:00:00"
    },
    {
      "experiment_id": "h002-amidar-s3",
      "hypothesis_id": "h002",
      "command": "python cleanrl/pqn_atari_envpool.py --env-id Amidar-v5 --seed 3 --total-timesteps 40000000 --hypothesis-id h002 --experiment-id h002-amidar-s3 --output-dir /runs",
      "cluster": "fir",
      "gpus": 1,
      "cpus": 8,
      "memory": "32G",
      "walltime": "11:00:00"
    },
    {
      "experiment_id": "h002-battlezone-s1",
      "hypothesis_id": "h002",
      "command": "python cleanrl/pqn_atari_envpool.py --env-id BattleZone-v5 --seed 1 --total-timesteps 40000000 --hypothesis-id h002 --experiment-id h002-battlezone-s1 --output-dir /runs",
      "cluster": "narval",
      "gpus": 1,
      "cpus": 8,
      "memory": "32G",
      "walltime": "11:00:00"
    },
    {
      "experiment_id": "h002-battlezone-s3",
      "hypothesis_id": "h002",
      "command": "python cleanrl/pqn_atari_envpool.py --env-id BattleZone-v5 --seed 3 --total-timesteps 40000000 --hypothesis-id h002 --experiment-id h002-battlezone-s3 --output-dir /runs",
      "cluster": "rorqual",
      "gpus": 1,
      "cpus": 8,
      "memory": "32G",
      "walltime": "11:00:00"
    },
    {
      "experiment_id": "h002-breakout-s1",
      "hypothesis_id": "h002",
      "command": "python cleanrl/pqn_atari_envpool.py --env-id Breakout-v5 --seed 1 --total-timesteps 40000000 --hypothesis-id h002 --experiment-id h002-breakout-s1 --output-dir /runs",
      "cluster": "nibi",
      "gpus": 1,
      "cpus": 8,
      "memory": "32G",
      "walltime": "11:00:00"
    },
    {
      "experiment_id": "h002-namethisgame-s1",
      "hypothesis_id": "h002",
      "command": "python cleanrl/pqn_atari_envpool.py --env-id NameThisGame-v5 --seed 1 --total-timesteps 40000000 --hypothesis-id h002 --experiment-id h002-namethisgame-s1 --output-dir /runs",
      "cluster": "fir",
      "gpus": 1,
      "cpus": 8,
      "memory": "32G",
      "walltime": "11:00:00"
    },
    {
      "experiment_id": "h002-namethisgame-s3",
      "hypothesis_id": "h002",
      "command": "python cleanrl/pqn_atari_envpool.py --env-id NameThisGame-v5 --seed 3 --total-timesteps 40000000 --hypothesis-id h002 --experiment-id h002-namethisgame-s3 --output-dir /runs",
      "cluster": "narval",
      "gpus": 1,
      "cpus": 8,
      "memory": "32G",
      "walltime": "11:00:00"
    },
    {
      "experiment_id": "h002-solaris-s1",
      "hypothesis_id": "h002",
      "command": "python cleanrl/pqn_atari_envpool.py --env-id Solaris-v5 --seed 1 --total-timesteps 40000000 --hypothesis-id h002 --experiment-id h002-solaris-s1 --output-dir /runs",
      "cluster": "rorqual",
      "gpus": 1,
      "cpus": 8,
      "memory": "32G",
      "walltime": "11:00:00"
    }
  ]
}