{
  "experiments": [
    {
      "cluster": "rorqual",
      "experiment_id": "h064-asterix-s1",
      "hypothesis_id": "h064",
      "command": "python cleanrl/dqn_atari_envpool_rainbow_lite.py --env-id Asterix-v5 --seed 1 --hypothesis-id h064 --experiment-id h064-asterix-s1 --output-dir /runs",
      "gpus": 1,
      "gpu_type": "h100",
      "cpus": 8,
      "memory": "48G",
      "walltime": "11:00:00"
    },
    {
      "cluster": "rorqual",
      "experiment_id": "h064-pong-s2",
      "hypothesis_id": "h064",
      "command": "python cleanrl/dqn_atari_envpool_rainbow_lite.py --env-id Pong-v5 --seed 2 --hypothesis-id h064 --experiment-id h064-pong-s2 --output-dir /runs",
      "gpus": 1,
      "gpu_type": "h100",
      "cpus": 8,
      "memory": "48G",
      "walltime": "11:00:00"
    },
    {
      "cluster": "rorqual",
      "experiment_id": "h064-gopher-s1",
      "hypothesis_id": "h064",
      "command": "python cleanrl/dqn_atari_envpool_rainbow_lite.py --env-id Gopher-v5 --seed 1 --hypothesis-id h064 --experiment-id h064-gopher-s1 --output-dir /runs",
      "gpus": 1,
      "gpu_type": "h100",
      "cpus": 8,
      "memory": "48G",
      "walltime": "11:00:00"
    }
  ]
}
